reactord/__init__.py
reactord/flowreactors/__init__.py
reactord/flowreactors/stationary_1d/__init__.py
reactord/flowreactors/stationary_1d/pfr/__init__.py
reactord/flowreactors/stationary_1d/pfr/pfr.py
reactord/flowreactors/stationary_1d/pfr/energy_balances/__init__.py
reactord/flowreactors/stationary_1d/pfr/energy_balances/adiabatic.py
reactord/flowreactors/stationary_1d/pfr/energy_balances/isothermic.py
reactord/flowreactors/stationary_1d/pfr/energy_balances/noisothermic_all_constant.py
reactord/flowreactors/stationary_1d/pfr/energy_balances/noisothermic_u_constant.py
reactord/flowreactors/stationary_1d/pfr/mass_balances/__init__.py
reactord/flowreactors/stationary_1d/pfr/mass_balances/molarflow.py
reactord/flowreactors/stationary_1d/pfr/pressure_balances/__init__.py
reactord/flowreactors/stationary_1d/pfr/pressure_balances/ergun.py
reactord/flowreactors/stationary_1d/pfr/pressure_balances/isobaric.py
reactord/kinetic/__init__.py
reactord/kinetic/argument.py
reactord/kinetic/kinetic.py
reactord/kinetic/matrix_builder.py
reactord/kinetic/reaction_enthalpy.py
reactord/mix/__init__.py
reactord/mix/abstract_mix.py
reactord/mix/ideal_gas.py
reactord/mix/ideal_solution.py
reactord/mix/viscosity_mixing_rules/__init__.py
reactord/mix/viscosity_mixing_rules/grunbergnissan.py
reactord/mix/viscosity_mixing_rules/herningzipperer.py
reactord/mix/viscosity_mixing_rules/linearmix.py
reactord/substance/__init__.py
reactord/substance/substance.py
reactord/substance/symbolic.py
reactord/substance/thermo_substance.py
reactord-0.0.1b4.dist-info/LICENCE
reactord-0.0.1b4.dist-info/METADATA
reactord-0.0.1b4.dist-info/WHEEL
reactord-0.0.1b4.dist-info/top_level.txt
reactord-0.0.1b4.dist-info/RECORD
