Metadata-Version: 2.1
Name: reactord
Version: 0.0.1b4
Summary: Package for the simulation and design of chemical reactors
Author-email: "Brandolín, Salvador Eduardo" <salvadorebrandolin@mi.unc.edu.ar>, "Parodi, Adrián" <adrian.parodi@mi.unc.edu.ar>, "Rovezzi, Juan Pablo" <juan.rovezzi@mi.unc.edu.ar>, "Santos, Maricel Del Valle" <maricel.santos@mi.unc.edu.ar>, "Scilipoti, José Antonio" <jscilipoti@unc.edu.ar>
License: The MIT License
Project-URL: Homepage, https://github.com/SalvadorBrandolin/reactord
Keywords: chemical reactor,reactor design,reactor simulation,chemical engineering
Classifier: Development Status :: 4 - Beta
Classifier: Intended Audience :: Education
Classifier: Intended Audience :: Science/Research
Classifier: License :: OSI Approved :: MIT License
Classifier: Operating System :: OS Independent
Classifier: Programming Language :: Python
Classifier: Programming Language :: Python :: 3.10
Classifier: Topic :: Scientific/Engineering
License-File: LICENCE
Requires-Dist: ipython
Requires-Dist: dill (>=0.3.6)
Requires-Dist: numpy (>=1.24.3)
Requires-Dist: pandas (>=2.0.1)
Requires-Dist: scipy (>=1.10.1)
Requires-Dist: sympy (>=1.12)
Requires-Dist: thermo (>=0.2.24)
